{
  "chainId": 8453,
  "prizePoolAddress": "0x45b2010d8A4f08b53c9fa7544C51dFd9733732cb",
  "vaultAddress": "0x327b2ea9668a552fe5dec8e3c6e47e540a0a58c6",
  "userAddresses": [
    "0x327b2ea9668a552fe5dec8e3c6e47e540a0a58c6"
  ],
  "winners": [
    {
      "user": "0x327b2ea9668a552fe5dec8e3c6e47e540a0a58c6",
      "prizes": {
        "6": [
          3,
          21,
          26,
          38,
          47,
          81,
          118,
          137,
          145,
          152,
          153,
          156,
          170,
          230,
          240,
          290,
          336,
          340,
          431,
          440,
          473,
          530,
          541,
          552,
          570,
          626,
          643,
          727,
          744,
          788,
          807,
          840,
          860,
          923,
          924,
          950,
          998,
          1003,
          1019,
          1057,
          1081,
          1115,
          1151,
          1157,
          1161,
          1223,
          1232,
          1241,
          1249,
          1264,
          1295,
          1305,
          1317,
          1345,
          1353,
          1359,
          1374,
          1387,
          1395,
          1399,
          1403,
          1405,
          1411,
          1446,
          1460,
          1474,
          1481,
          1507,
          1510,
          1524,
          1580,
          1592,
          1643,
          1662,
          1672,
          1708,
          1715,
          1723,
          1736,
          1753,
          1763,
          1774,
          1782,
          1795,
          1796,
          1844,
          1848,
          1869,
          1870,
          1873,
          1881,
          1962,
          1975,
          1984,
          2012,
          2057,
          2065,
          2077,
          2086,
          2095,
          2100,
          2119,
          2148,
          2164,
          2167,
          2172,
          2187,
          2216,
          2261,
          2265,
          2284,
          2316,
          2351,
          2374,
          2398,
          2403,
          2436,
          2482,
          2514,
          2522,
          2525,
          2536,
          2599,
          2621,
          2629,
          2669,
          2673,
          2717,
          2770,
          2771,
          2808,
          2809,
          2841,
          2853,
          2891,
          2896,
          2923,
          2943,
          2946,
          2978,
          2988,
          2989,
          2993,
          3014,
          3026,
          3071,
          3072,
          3120,
          3124,
          3169,
          3173,
          3186,
          3195,
          3236,
          3272,
          3330,
          3332,
          3341,
          3426,
          3474,
          3487,
          3493,
          3500,
          3501,
          3525,
          3553,
          3579,
          3615,
          3619,
          3651,
          3670,
          3681,
          3683,
          3711,
          3730,
          3758,
          3770,
          3774,
          3801,
          3827,
          3828,
          3854,
          3878,
          3891,
          3920,
          3924,
          3963,
          4006,
          4023,
          4037,
          4051,
          4063,
          4074,
          4081
        ]
      }
    }
  ]
}